optimus/__init__.py
optimus/__main__.py
optimus_py-1.3.dist-info/LICENCE
optimus_py-1.3.dist-info/METADATA
optimus_py-1.3.dist-info/WHEEL
optimus_py-1.3.dist-info/top_level.txt
optimus_py-1.3.dist-info/RECORD
