Metadata-Version: 2.1
Name: optimus-py
Version: 1.3
Summary: Code optimization documentation & timing module
Home-page: https://github.com/kavinbharathii/
Author: Kavin Bharathi
Author-email: r.m.kavinbharathi@gmail.com
Requires-Python: >=3.5
License-File: LICENCE
Requires-Dist: rich (>=12.5.1)
